mkdocs_blogging_plugin/__init__.py
mkdocs_blogging_plugin/config.py
mkdocs_blogging_plugin/plugin.py
mkdocs_blogging_plugin/util.py
mkdocs_blogging_plugin/templates/blog-button-theme.html
mkdocs_blogging_plugin/templates/blog-card-theme.html
mkdocs_blogging_plugin/templates/blog-tags-index.html
mkdocs_blogging_plugin/templates/blog-tags-render.html
mkdocs_blogging_plugin/templates/blog-tags.html
mkdocs_blogging_plugin/templates/blog.html
mkdocs_blogging_plugin/templates/pagination.js
tests/__init__.py
tests/test_config.py
tests/test_format.py
tests/test_template.py
mkdocs_blogging_plugin-2.2.11.dist-info/LICENSE
mkdocs_blogging_plugin-2.2.11.dist-info/METADATA
mkdocs_blogging_plugin-2.2.11.dist-info/WHEEL
mkdocs_blogging_plugin-2.2.11.dist-info/entry_points.txt
mkdocs_blogging_plugin-2.2.11.dist-info/top_level.txt
mkdocs_blogging_plugin-2.2.11.dist-info/RECORD
