Metadata-Version: 2.1
Name: mkdocs-blogging-plugin
Version: 2.2.11
Summary: Mkdocs plugin that generates a blog index page sorted by creation date.
Author: Liang Yesheang
Author-email: liang2kl@outlook.com
License: MIT
Project-URL: Source, https://github.com/liang2kl/mkdocs-blogging-plugin
Keywords: mkdocs blog plugin
Classifier: Development Status :: 5 - Production/Stable
Classifier: Programming Language :: Python :: 3
Classifier: Programming Language :: Python :: 3.6
Classifier: Programming Language :: Python :: 3.7
Classifier: Programming Language :: Python :: 3.8
Classifier: Programming Language :: Python :: 3.9
Classifier: License :: OSI Approved :: MIT License
Classifier: Operating System :: OS Independent
Requires-Python: >=3.6
License-File: LICENSE
